andriatina_auth/__init__.py
andriatina_auth/andriatina_auth.py
andriatina_authenticator-0.1.1.dist-info/METADATA
andriatina_authenticator-0.1.1.dist-info/WHEEL
andriatina_authenticator-0.1.1.dist-info/top_level.txt
andriatina_authenticator-0.1.1.dist-info/RECORD
