Metadata-Version: 2.1
Name: andriatina-authenticator
Version: 0.1.1
Summary: authentificator
Home-page: UNKNOWN
Author: andriatina
Author-email: andriatina@aims.ac.za
License: Universite of Antananarivo
Platform: UNKNOWN
Classifier: Development Status :: 3 - Alpha
Classifier: Intended Audience :: Education
Classifier: Programming Language :: Python :: 2
Classifier: Programming Language :: Python :: 3
Classifier: Operating System :: MacOS :: MacOS X
Classifier: Operating System :: Microsoft :: Windows
Requires-Dist: pyotp
